datathing/__init__.py
datathing/core.py
datathing-0.1.2.dist-info/METADATA
datathing-0.1.2.dist-info/WHEEL
datathing-0.1.2.dist-info/top_level.txt
datathing-0.1.2.dist-info/RECORD
