Metadata-Version: 2.4
Name: datathing
Version: 0.1.2
Summary: Модуль для автоматического анализа и визуализации табличных данных
Author-email: Артем Грачев <artemy.develop@gmail.com>
Project-URL: GitHub, https://github.com/Artemy-dev/datathing
Requires-Python: >=3.8
Requires-Dist: numpy
Requires-Dist: pandas
Requires-Dist: scipy
Requires-Dist: matplotlib
Requires-Dist: seaborn
Requires-Dist: statsmodels
